[
    {
        "car_year": 2020,
        "car_count": 1
    },
    {
        "car_year": 2019,
        "car_count": 9
    },
    {
        "car_year": 2018,
        "car_count": 14
    },
    {
        "car_year": 2017,
        "car_count": 13
    },
    {
        "car_year": 2016,
        "car_count": 17
    },
    {
        "car_year": 2015,
        "car_count": 8
    },
    {
        "car_year": 2014,
        "car_count": 11
    },
    {
        "car_year": 2013,
        "car_count": 9
    },
    {
        "car_year": 2011,
        "car_count": 1
    },
    {
        "car_year": 2009,
        "car_count": 2
    },
    {
        "car_year": 2008,
        "car_count": 2
    },
    {
        "car_year": 2007,
        "car_count": 1
    },
    {
        "car_year": 2002,
        "car_count": 2
    },
    {
        "car_year": 1995,
        "car_count": 1
    }
]